{"map": "Waystation", "baseBuild": 28667, "expansion": "HotS", "frames": 15184, "message": "", "category": "Private", "map_hash": "e5a652fc426ac615be18e652995d5a42c5f109a8d89e6c359c6f262ab7bcd52f", "include_map_details": false, "game_type": "1v1", "players": {"1": {"abilities": [], "uid": 2341765, "is_human": true, "supply": [[0, 6], [1, 6], [160, 7], [320, 8], [480, 8], [640, 9], [800, 9], [960, 10], [1120, 10], [1280, 11], [1440, 12], [1600, 12], [1760, 13], [1920, 14], [2080, 15], [2240, 15], [2400, 16], [2560, 17], [2720, 17], [2880, 18], [3040, 18], [3200, 18], [3360, 18], [3520, 18], [3680, 19], [3840, 20], [4000, 20], [4160, 21], [4320, 22], [4480, 23], [4640, 24], [4800, 26], [4960, 26], [5120, 28], [5280, 30], [5440, 30], [5600, 34], [5760, 35], [5920, 37], [6080, 38], [6240, 40], [6400, 41], [6560, 44], [6720, 46], [6880, 48], [7040, 52], [7200, 53], [7360, 56], [7520, 57], [7680, 60], [7840, 63], [8000, 63], [8160, 67], [8320, 68], [8480, 69], [8640, 71], [8800, 71], [8960, 73], [9120, 74], [9280, 81], [9440, 82], [9600, 83], [9760, 84], [9920, 86], [10080, 86], [10240, 88], [10400, 94], [10560, 94], [10720, 94], [10880, 95], [11040, 95], [11200, 96], [11360, 97], [11520, 105], [11680, 105], [11840, 111], [12000, 115], [12160, 123], [12320, 125], [12480, 125], [12640, 141], [12800, 142], [12960, 146], [13120, 146], [13280, 162], [13440, 166], [13600, 166], [13760, 174], [13920, 178], [14080, 186], [14240, 175], [14400, 153], [14560, 137], [14720, 138], [14880, 134], [15040, 131], [15061, 131]], "handicap": 100, "is_winner": true, "pick_race": "Protoss", "unitsLost": [{"frame": 3022, "killer": 1, "name": "Pylon", "clock_position": null, "time": "3:08"}, {"frame": 11386, "killer": 2, "name": "Phoenix", "clock_position": null, "time": "11:51"}, {"frame": 12173, "killer": 2, "name": "Phoenix", "clock_position": null, "time": "12:40"}, {"frame": 12440, "killer": 2, "name": "Phoenix", "clock_position": null, "time": "12:57"}, {"frame": 13790, "killer": 2, "name": "Phoenix", "clock_position": null, "time": "14:21"}, {"frame": 14126, "killer": 2, "name": "Zealot", "clock_position": null, "time": "14:42"}, {"frame": 14157, "killer": 2, "name": "Zealot", "clock_position": null, "time": "14:44"}, {"frame": 14216, "killer": 2, "name": "Probe", "clock_position": null, "time": "14:48"}, {"frame": 14219, "killer": 2, "name": "Probe", "clock_position": null, "time": "14:48"}, {"frame": 14222, "killer": 2, "name": "Stalker", "clock_position": null, "time": "14:48"}, {"frame": 14225, "killer": 2, "name": "Stalker", "clock_position": null, "time": "14:49"}, {"frame": 14237, "killer": 2, "name": "Probe", "clock_position": null, "time": "14:49"}, {"frame": 14250, "killer": 2, "name": "Zealot", "clock_position": null, "time": "14:50"}, {"frame": 14259, "killer": 2, "name": "Stalker", "clock_position": null, "time": "14:51"}, {"frame": 14260, "killer": 2, "name": "Stalker", "clock_position": null, "time": "14:51"}, {"frame": 14264, "killer": 2, "name": "Zealot", "clock_position": null, "time": "14:51"}, {"frame": 14273, "killer": 2, "name": "Colossus", "clock_position": null, "time": "14:52"}, {"frame": 14292, "killer": 2, "name": "Stalker", "clock_position": null, "time": "14:53"}, {"frame": 14310, "killer": 2, "name": "Stalker", "clock_position": null, "time": "14:54"}, {"frame": 14326, "killer": 2, "name": "Stalker", "clock_position": null, "time": "14:55"}, {"frame": 14344, "killer": 2, "name": "Stalker", "clock_position": null, "time": "14:56"}, {"frame": 14364, "killer": 2, "name": "Stalker", "clock_position": null, "time": "14:57"}, {"frame": 14365, "killer": 2, "name": "Stalker", "clock_position": null, "time": "14:57"}, {"frame": 14378, "killer": 2, "name": "Stalker", "clock_position": null, "time": "14:58"}, {"frame": 14378, "killer": 2, "name": "Stalker", "clock_position": null, "time": "14:58"}, {"frame": 14409, "killer": 2, "name": "Assimilator", "clock_position": null, "time": "15:00"}, {"frame": 14411, "killer": 2, "name": "Stalker", "clock_position": null, "time": "15:00"}, {"frame": 14414, "killer": 2, "name": "Colossus", "clock_position": null, "time": "15:00"}, {"frame": 14419, "killer": 2, "name": "Stalker", "clock_position": null, "time": "15:01"}, {"frame": 14457, "killer": 2, "name": "Stalker", "clock_position": null, "time": "15:03"}, {"frame": 14480, "killer": 2, "name": "Stalker", "clock_position": null, "time": "15:05"}, {"frame": 14489, "killer": 2, "name": "Colossus", "clock_position": null, "time": "15:05"}, {"frame": 14505, "killer": 2, "name": "Phoenix", "clock_position": null, "time": "15:06"}, {"frame": 14513, "killer": 2, "name": "Phoenix", "clock_position": null, "time": "15:07"}, {"frame": 14537, "killer": 2, "name": "Pylon", "clock_position": null, "time": "15:08"}, {"frame": 14692, "killer": 2, "name": "Probe", "clock_position": null, "time": "15:18"}, {"frame": 14725, "killer": 2, "name": "Probe", "clock_position": null, "time": "15:20"}, {"frame": 14779, "killer": 2, "name": "Probe", "clock_position": null, "time": "15:23"}, {"frame": 14785, "killer": 2, "name": "Probe", "clock_position": null, "time": "15:24"}, {"frame": 14814, "killer": 2, "name": "Probe", "clock_position": null, "time": "15:25"}, {"frame": 14844, "killer": 2, "name": "Probe", "clock_position": null, "time": "15:27"}, {"frame": 14845, "killer": 2, "name": "Probe", "clock_position": null, "time": "15:27"}, {"frame": 14851, "killer": 2, "name": "Probe", "clock_position": null, "time": "15:28"}, {"frame": 14878, "killer": 2, "name": "Probe", "clock_position": null, "time": "15:29"}, {"frame": 14888, "killer": 2, "name": "Probe", "clock_position": null, "time": "15:30"}, {"frame": 14910, "killer": 2, "name": "Probe", "clock_position": null, "time": "15:31"}, {"frame": 14911, "killer": 2, "name": "Probe", "clock_position": null, "time": "15:31"}, {"frame": 14923, "killer": 2, "name": "Probe", "clock_position": null, "time": "15:32"}, {"frame": 14944, "killer": 2, "name": "Probe", "clock_position": null, "time": "15:34"}, {"frame": 14976, "killer": 2, "name": "Probe", "clock_position": null, "time": "15:36"}, {"frame": 14997, "killer": 2, "name": "Stalker", "clock_position": null, "time": "15:37"}, {"frame": 14999, "killer": 2, "name": "Probe", "clock_position": null, "time": "15:37"}, {"frame": 15011, "killer": 2, "name": "Probe", "clock_position": null, "time": "15:38"}, {"frame": 15031, "killer": 2, "name": "Probe", "clock_position": null, "time": "15:39"}], "result": "Win", "league": 8, "buildOrder": [{"is_worker": true, "name": "Probe", "clock_position": null, "supply": 6, "frame": 8, "time": "0:00"}, {"is_worker": true, "name": "Probe", "clock_position": null, "supply": 7, "frame": 279, "time": "0:17"}, {"is_worker": true, "name": "Probe", "clock_position": null, "supply": 8, "frame": 550, "time": "0:34"}, {"is_worker": false, "name": "Pylon", "clock_position": null, "supply": 9, "frame": 777, "time": "0:48"}, {"is_worker": true, "name": "Probe", "clock_position": null, "supply": 9, "frame": 926, "time": "0:57"}, {"is_worker": true, "name": "Probe", "clock_position": null, "supply": 10, "frame": 1107, "time": "1:09"}, {"is_worker": true, "name": "Probe", "clock_position": null, "supply": 11, "frame": 1311, "time": "1:21"}, {"is_worker": true, "name": "Probe", "clock_position": null, "supply": 12, "frame": 1593, "time": "1:39"}, {"is_worker": false, "name": "Forge", "clock_position": null, "supply": 12, "frame": 1605, "time": "1:40"}, {"is_worker": true, "name": "Probe", "clock_position": null, "supply": 13, "frame": 1788, "time": "1:51"}, {"is_worker": true, "name": "Probe", "clock_position": null, "supply": 14, "frame": 2035, "time": "2:07"}, {"is_worker": true, "name": "Probe", "clock_position": null, "supply": 15, "frame": 2216, "time": "2:18"}, {"is_worker": true, "name": "Probe", "clock_position": null, "supply": 16, "frame": 2442, "time": "2:32"}, {"is_worker": false, "name": "Pylon", "clock_position": null, "supply": 17, "frame": 2635, "time": "2:44"}, {"is_worker": true, "name": "Probe", "clock_position": null, "supply": 17, "frame": 2823, "time": "2:56"}, {"is_worker": false, "name": "Nexus", "clock_position": null, "supply": 18, "frame": 3079, "time": "3:12"}, {"is_worker": false, "name": "Pylon", "clock_position": null, "supply": 18, "frame": 3144, "time": "3:16"}, {"is_worker": false, "name": "Gateway", "clock_position": null, "supply": 18, "frame": 3270, "time": "3:24"}, {"is_worker": false, "name": "PhotonCannon", "clock_position": null, "supply": 18, "frame": 3452, "time": "3:35"}, {"is_worker": true, "name": "Probe", "clock_position": null, "supply": 18, "frame": 3557, "time": "3:42"}, {"is_worker": false, "name": "Assimilator", "clock_position": null, "supply": 18, "frame": 3632, "time": "3:47"}, {"is_worker": true, "name": "Probe", "clock_position": null, "supply": 19, "frame": 3738, "time": "3:53"}, {"is_worker": true, "name": "Probe", "clock_position": null, "supply": 20, "frame": 3946, "time": "4:06"}, {"is_worker": true, "name": "Probe", "clock_position": null, "supply": 20, "frame": 4127, "time": "4:17"}, {"is_worker": false, "name": "Assimilator", "clock_position": null, "supply": 21, "frame": 4176, "time": "4:21"}, {"is_worker": false, "name": "Assimilator", "clock_position": null, "supply": 21, "frame": 4207, "time": "4:22"}, {"is_worker": true, "name": "Probe", "clock_position": null, "supply": 22, "frame": 4336, "time": "4:31"}, {"is_worker": true, "name": "Probe", "clock_position": null, "supply": 23, "frame": 4521, "time": "4:42"}, {"is_worker": false, "name": "CyberneticsCore", "clock_position": null, "supply": 23, "frame": 4563, "time": "4:45"}, {"is_worker": true, "name": "Probe", "clock_position": null, "supply": 24, "frame": 4700, "time": "4:53"}, {"is_worker": true, "name": "Probe", "clock_position": null, "supply": 24, "frame": 4718, "time": "4:54"}, {"is_worker": true, "name": "Probe", "clock_position": null, "supply": 26, "frame": 4958, "time": "5:09"}, {"is_worker": true, "name": "Probe", "clock_position": null, "supply": 26, "frame": 4971, "time": "5:10"}, {"is_worker": false, "name": "Assimilator", "clock_position": null, "supply": 26, "frame": 5010, "time": "5:13"}, {"is_worker": true, "name": "Probe", "clock_position": null, "supply": 28, "frame": 5139, "time": "5:21"}, {"is_worker": true, "name": "Probe", "clock_position": null, "supply": 28, "frame": 5242, "time": "5:27"}, {"is_worker": false, "name": "Pylon", "clock_position": null, "supply": 30, "frame": 5332, "time": "5:33"}, {"is_worker": false, "name": "Stargate", "clock_position": null, "supply": 30, "frame": 5399, "time": "5:37"}, {"is_worker": true, "name": "Probe", "clock_position": null, "supply": 30, "frame": 5416, "time": "5:38"}, {"is_worker": true, "name": "Probe", "clock_position": null, "supply": 30, "frame": 5513, "time": "5:44"}, {"is_worker": false, "name": "Sentry", "clock_position": null, "supply": 30, "frame": 5592, "time": "5:49"}, {"is_worker": true, "name": "Probe", "clock_position": null, "supply": 34, "frame": 5633, "time": "5:52"}, {"is_worker": true, "name": "Probe", "clock_position": null, "supply": 34, "frame": 5703, "time": "5:56"}, {"is_worker": true, "name": "Probe", "clock_position": null, "supply": 35, "frame": 5814, "time": "6:03"}, {"is_worker": true, "name": "Probe", "clock_position": null, "supply": 35, "frame": 5895, "time": "6:08"}, {"is_worker": false, "name": "RoboticsFacility", "clock_position": null, "supply": 37, "frame": 5958, "time": "6:12"}, {"is_worker": false, "name": "Pylon", "clock_position": null, "supply": 37, "frame": 6048, "time": "6:18"}, {"is_worker": true, "name": "Probe", "clock_position": null, "supply": 37, "frame": 6070, "time": "6:19"}, {"is_worker": false, "name": "WarpGateResearch", "clock_position": null, "supply": 38, "frame": 6109, "time": "6:21"}, {"is_worker": true, "name": "Probe", "clock_position": null, "supply": 38, "frame": 6166, "time": "6:25"}, {"is_worker": false, "name": "Phoenix", "clock_position": null, "supply": 40, "frame": 6263, "time": "6:31"}, {"is_worker": true, "name": "Probe", "clock_position": null, "supply": 40, "frame": 6341, "time": "6:36"}, {"is_worker": false, "name": "Pylon", "clock_position": null, "supply": 40, "frame": 6355, "time": "6:37"}, {"is_worker": true, "name": "Probe", "clock_position": null, "supply": 41, "frame": 6437, "time": "6:42"}, {"is_worker": true, "name": "Probe", "clock_position": null, "supply": 44, "frame": 6612, "time": "6:53"}, {"is_worker": false, "name": "Phoenix", "clock_position": null, "supply": 44, "frame": 6690, "time": "6:58"}, {"is_worker": true, "name": "Probe", "clock_position": null, "supply": 44, "frame": 6708, "time": "6:59"}, {"is_worker": false, "name": "WarpPrism", "clock_position": null, "supply": 46, "frame": 6844, "time": "7:07"}, {"is_worker": true, "name": "Probe", "clock_position": null, "supply": 48, "frame": 6883, "time": "7:10"}, {"is_worker": true, "name": "Probe", "clock_position": null, "supply": 48, "frame": 6979, "time": "7:16"}, {"is_worker": false, "name": "Pylon", "clock_position": null, "supply": 52, "frame": 7049, "time": "7:20"}, {"is_worker": false, "name": "Phoenix", "clock_position": null, "supply": 52, "frame": 7075, "time": "7:22"}, {"is_worker": true, "name": "Probe", "clock_position": null, "supply": 52, "frame": 7154, "time": "7:27"}, {"is_worker": true, "name": "Probe", "clock_position": null, "supply": 53, "frame": 7250, "time": "7:33"}, {"is_worker": true, "name": "Probe", "clock_position": null, "supply": 56, "frame": 7425, "time": "7:44"}, {"is_worker": false, "name": "Pylon", "clock_position": null, "supply": 56, "frame": 7458, "time": "7:46"}, {"is_worker": false, "name": "Phoenix", "clock_position": null, "supply": 56, "frame": 7466, "time": "7:46"}, {"is_worker": true, "name": "Probe", "clock_position": null, "supply": 57, "frame": 7521, "time": "7:50"}, {"is_worker": false, "name": "MothershipCore", "clock_position": null, "supply": 60, "frame": 7792, "time": "8:07"}, {"is_worker": true, "name": "Probe", "clock_position": null, "supply": 60, "frame": 7807, "time": "8:07"}, {"is_worker": false, "name": "Phoenix", "clock_position": null, "supply": 63, "frame": 7898, "time": "8:13"}, {"is_worker": false, "name": "Pylon", "clock_position": null, "supply": 63, "frame": 7916, "time": "8:14"}, {"is_worker": false, "name": "Observer", "clock_position": null, "supply": 63, "frame": 8068, "time": "8:24"}, {"is_worker": false, "name": "RoboticsBay", "clock_position": null, "supply": 63, "frame": 8076, "time": "8:24"}, {"is_worker": true, "name": "Probe", "clock_position": null, "supply": 63, "frame": 8078, "time": "8:24"}, {"is_worker": true, "name": "Probe", "clock_position": null, "supply": 67, "frame": 8271, "time": "8:36"}, {"is_worker": true, "name": "Probe", "clock_position": null, "supply": 68, "frame": 8349, "time": "8:41"}, {"is_worker": false, "name": "Nexus", "clock_position": null, "supply": 68, "frame": 8362, "time": "8:42"}, {"is_worker": false, "name": "Pylon", "clock_position": null, "supply": 68, "frame": 8397, "time": "8:44"}, {"is_worker": false, "name": "ProtossGroundWeaponsLevel1", "clock_position": null, "supply": 68, "frame": 8457, "time": "8:48"}, {"is_worker": true, "name": "Probe", "clock_position": null, "supply": 69, "frame": 8542, "time": "8:53"}, {"is_worker": true, "name": "Probe", "clock_position": null, "supply": 69, "frame": 8620, "time": "8:58"}, {"is_worker": true, "name": "Probe", "clock_position": null, "supply": 71, "frame": 8813, "time": "9:10"}, {"is_worker": true, "name": "Probe", "clock_position": null, "supply": 71, "frame": 8891, "time": "9:15"}, {"is_worker": false, "name": "Assimilator", "clock_position": null, "supply": 71, "frame": 8910, "time": "9:16"}, {"is_worker": false, "name": "Colossus", "clock_position": null, "supply": 73, "frame": 8961, "time": "9:20"}, {"is_worker": false, "name": "ExtendedThermalLance", "clock_position": null, "supply": 73, "frame": 8987, "time": "9:21"}, {"is_worker": false, "name": "Assimilator", "clock_position": null, "supply": 73, "frame": 8995, "time": "9:22"}, {"is_worker": true, "name": "Probe", "clock_position": null, "supply": 73, "frame": 9084, "time": "9:27"}, {"is_worker": true, "name": "Probe", "clock_position": null, "supply": 74, "frame": 9169, "time": "9:33"}, {"is_worker": true, "name": "Probe", "clock_position": null, "supply": 81, "frame": 9355, "time": "9:44"}, {"is_worker": false, "name": "Gateway", "clock_position": null, "supply": 81, "frame": 9427, "time": "9:49"}, {"is_worker": true, "name": "Probe", "clock_position": null, "supply": 60, "frame": 9440, "time": "9:50"}, {"is_worker": false, "name": "Gateway", "clock_position": null, "supply": 82, "frame": 9455, "time": "9:50"}, {"is_worker": false, "name": "Gateway", "clock_position": null, "supply": 82, "frame": 9495, "time": "9:53"}, {"is_worker": true, "name": "Probe", "clock_position": null, "supply": 83, "frame": 9626, "time": "10:01"}, {"is_worker": false, "name": "Pylon", "clock_position": null, "supply": 83, "frame": 9665, "time": "10:04"}, {"is_worker": false, "name": "TwilightCouncil", "clock_position": null, "supply": 84, "frame": 9795, "time": "10:12"}, {"is_worker": true, "name": "Probe", "clock_position": null, "supply": 84, "frame": 9852, "time": "10:15"}, {"is_worker": true, "name": "Probe", "clock_position": null, "supply": 84, "frame": 9897, "time": "10:18"}, {"is_worker": false, "name": "BlinkTech", "clock_position": null, "supply": 86, "frame": 10028, "time": "10:26"}, {"is_worker": true, "name": "Probe", "clock_position": null, "supply": 86, "frame": 10123, "time": "10:32"}, {"is_worker": true, "name": "Probe", "clock_position": null, "supply": 86, "frame": 10168, "time": "10:35"}, {"is_worker": false, "name": "Colossus", "clock_position": null, "supply": 94, "frame": 10507, "time": "10:56"}, {"is_worker": false, "name": "Nexus", "clock_position": null, "supply": 94, "frame": 10572, "time": "11:00"}, {"is_worker": false, "name": "Gateway", "clock_position": null, "supply": 94, "frame": 10642, "time": "11:05"}, {"is_worker": false, "name": "Gateway", "clock_position": null, "supply": 94, "frame": 10649, "time": "11:05"}, {"is_worker": true, "name": "Probe", "clock_position": null, "supply": 94, "frame": 10802, "time": "11:15"}, {"is_worker": false, "name": "Gateway", "clock_position": null, "supply": 95, "frame": 10966, "time": "11:25"}, {"is_worker": false, "name": "ProtossGroundWeaponsLevel2", "clock_position": null, "supply": 95, "frame": 10994, "time": "11:27"}, {"is_worker": false, "name": "Gateway", "clock_position": null, "supply": 95, "frame": 11014, "time": "11:28"}, {"is_worker": false, "name": "Pylon", "clock_position": null, "supply": 95, "frame": 11046, "time": "11:30"}, {"is_worker": true, "name": "Probe", "clock_position": null, "supply": 95, "frame": 11073, "time": "11:32"}, {"is_worker": false, "name": "Gateway", "clock_position": null, "supply": 95, "frame": 11135, "time": "11:35"}, {"is_worker": false, "name": "Gateway", "clock_position": null, "supply": 95, "frame": 11177, "time": "11:38"}, {"is_worker": false, "name": "Pylon", "clock_position": null, "supply": 96, "frame": 11294, "time": "11:45"}, {"is_worker": true, "name": "Probe", "clock_position": null, "supply": 96, "frame": 11344, "time": "11:49"}, {"is_worker": false, "name": "Sentry", "clock_position": null, "supply": 97, "frame": 11449, "time": "11:55"}, {"is_worker": false, "name": "Sentry", "clock_position": null, "supply": 97, "frame": 11483, "time": "11:57"}, {"is_worker": false, "name": "Zealot", "clock_position": null, "supply": 97, "frame": 11494, "time": "11:58"}, {"is_worker": false, "name": "Zealot", "clock_position": null, "supply": 97, "frame": 11498, "time": "11:58"}, {"is_worker": false, "name": "Pylon", "clock_position": null, "supply": 105, "frame": 11555, "time": "12:02"}, {"is_worker": false, "name": "Colossus", "clock_position": null, "supply": 105, "frame": 11572, "time": "12:03"}, {"is_worker": false, "name": "Pylon", "clock_position": null, "supply": 105, "frame": 11776, "time": "12:16"}, {"is_worker": false, "name": "Stalker", "clock_position": null, "supply": 111, "frame": 11952, "time": "12:27"}, {"is_worker": false, "name": "Stalker", "clock_position": null, "supply": 111, "frame": 11956, "time": "12:27"}, {"is_worker": false, "name": "Stalker", "clock_position": null, "supply": 115, "frame": 12032, "time": "12:32"}, {"is_worker": false, "name": "Stalker", "clock_position": null, "supply": 115, "frame": 12036, "time": "12:32"}, {"is_worker": false, "name": "Stalker", "clock_position": null, "supply": 115, "frame": 12039, "time": "12:32"}, {"is_worker": false, "name": "Stalker", "clock_position": null, "supply": 115, "frame": 12043, "time": "12:32"}, {"is_worker": false, "name": "WarpPrism", "clock_position": null, "supply": 115, "frame": 12134, "time": "12:38"}, {"is_worker": false, "name": "Pylon", "clock_position": null, "supply": 115, "frame": 12140, "time": "12:38"}, {"is_worker": false, "name": "Pylon", "clock_position": null, "supply": 115, "frame": 12143, "time": "12:38"}, {"is_worker": false, "name": "Stalker", "clock_position": null, "supply": 123, "frame": 12258, "time": "12:46"}, {"is_worker": false, "name": "Stalker", "clock_position": null, "supply": 123, "frame": 12261, "time": "12:46"}, {"is_worker": false, "name": "Stalker", "clock_position": null, "supply": 125, "frame": 12480, "time": "13:00"}, {"is_worker": false, "name": "Stalker", "clock_position": null, "supply": 125, "frame": 12485, "time": "13:00"}, {"is_worker": false, "name": "Stalker", "clock_position": null, "supply": 125, "frame": 12487, "time": "13:00"}, {"is_worker": false, "name": "Stalker", "clock_position": null, "supply": 125, "frame": 12490, "time": "13:00"}, {"is_worker": false, "name": "Stalker", "clock_position": null, "supply": 125, "frame": 12624, "time": "13:09"}, {"is_worker": false, "name": "Stalker", "clock_position": null, "supply": 125, "frame": 12629, "time": "13:09"}, {"is_worker": false, "name": "Stalker", "clock_position": null, "supply": 125, "frame": 12631, "time": "13:09"}, {"is_worker": false, "name": "Stalker", "clock_position": null, "supply": 125, "frame": 12638, "time": "13:09"}, {"is_worker": false, "name": "Observer", "clock_position": null, "supply": 141, "frame": 12722, "time": "13:15"}, {"is_worker": false, "name": "Pylon", "clock_position": null, "supply": 141, "frame": 12786, "time": "13:19"}, {"is_worker": false, "name": "Stalker", "clock_position": null, "supply": 142, "frame": 12878, "time": "13:24"}, {"is_worker": false, "name": "Stalker", "clock_position": null, "supply": 142, "frame": 12880, "time": "13:25"}, {"is_worker": false, "name": "WarpPrism", "clock_position": null, "supply": 146, "frame": 12995, "time": "13:32"}, {"is_worker": false, "name": "Stalker", "clock_position": null, "supply": 146, "frame": 13148, "time": "13:41"}, {"is_worker": false, "name": "Stalker", "clock_position": null, "supply": 146, "frame": 13152, "time": "13:42"}, {"is_worker": false, "name": "Stalker", "clock_position": null, "supply": 146, "frame": 13155, "time": "13:42"}, {"is_worker": false, "name": "Stalker", "clock_position": null, "supply": 146, "frame": 13159, "time": "13:42"}, {"is_worker": false, "name": "Stalker", "clock_position": null, "supply": 146, "frame": 13162, "time": "13:42"}, {"is_worker": false, "name": "Stalker", "clock_position": null, "supply": 146, "frame": 13164, "time": "13:42"}, {"is_worker": false, "name": "Stalker", "clock_position": null, "supply": 146, "frame": 13198, "time": "13:44"}, {"is_worker": false, "name": "Stalker", "clock_position": null, "supply": 146, "frame": 13202, "time": "13:45"}, {"is_worker": false, "name": "Pylon", "clock_position": null, "supply": 162, "frame": 13304, "time": "13:51"}, {"is_worker": false, "name": "Stalker", "clock_position": null, "supply": 162, "frame": 13417, "time": "13:58"}, {"is_worker": false, "name": "Stalker", "clock_position": null, "supply": 162, "frame": 13420, "time": "13:58"}, {"is_worker": false, "name": "Pylon", "clock_position": null, "supply": 166, "frame": 13609, "time": "14:10"}, {"is_worker": false, "name": "Stalker", "clock_position": null, "supply": 166, "frame": 13660, "time": "14:13"}, {"is_worker": false, "name": "Stalker", "clock_position": null, "supply": 166, "frame": 13664, "time": "14:14"}, {"is_worker": false, "name": "Stalker", "clock_position": null, "supply": 166, "frame": 13666, "time": "14:14"}, {"is_worker": false, "name": "Stalker", "clock_position": null, "supply": 166, "frame": 13669, "time": "14:14"}, {"is_worker": false, "name": "Zealot", "clock_position": null, "supply": 174, "frame": 13890, "time": "14:28"}, {"is_worker": false, "name": "Zealot", "clock_position": null, "supply": 174, "frame": 13894, "time": "14:28"}, {"is_worker": false, "name": "Pylon", "clock_position": null, "supply": 178, "frame": 13938, "time": "14:31"}, {"is_worker": false, "name": "WarpPrism", "clock_position": null, "supply": 178, "frame": 13974, "time": "14:33"}, {"is_worker": false, "name": "Stalker", "clock_position": null, "supply": 178, "frame": 14031, "time": "14:36"}, {"is_worker": false, "name": "Stalker", "clock_position": null, "supply": 178, "frame": 14034, "time": "14:37"}, {"is_worker": false, "name": "Stalker", "clock_position": null, "supply": 178, "frame": 14038, "time": "14:37"}, {"is_worker": false, "name": "Stalker", "clock_position": null, "supply": 178, "frame": 14040, "time": "14:37"}, {"is_worker": false, "name": "Stalker", "clock_position": null, "supply": 175, "frame": 14275, "time": "14:52"}, {"is_worker": false, "name": "Stalker", "clock_position": null, "supply": 175, "frame": 14279, "time": "14:52"}, {"is_worker": false, "name": "Stalker", "clock_position": null, "supply": 175, "frame": 14281, "time": "14:52"}, {"is_worker": false, "name": "Stalker", "clock_position": null, "supply": 175, "frame": 14284, "time": "14:52"}, {"is_worker": false, "name": "Stalker", "clock_position": null, "supply": 153, "frame": 14402, "time": "15:00"}, {"is_worker": false, "name": "Stalker", "clock_position": null, "supply": 153, "frame": 14405, "time": "15:00"}, {"is_worker": false, "name": "Stalker", "clock_position": null, "supply": 153, "frame": 14553, "time": "15:09"}, {"is_worker": false, "name": "Stalker", "clock_position": null, "supply": 153, "frame": 14557, "time": "15:09"}, {"is_worker": false, "name": "Stalker", "clock_position": null, "supply": 137, "frame": 14592, "time": "15:12"}, {"is_worker": false, "name": "Stalker", "clock_position": null, "supply": 138, "frame": 14721, "time": "15:20"}, {"is_worker": false, "name": "Stalker", "clock_position": null, "supply": 138, "frame": 14726, "time": "15:20"}, {"is_worker": false, "name": "Stalker", "clock_position": null, "supply": 134, "frame": 14954, "time": "15:34"}, {"is_worker": false, "name": "Stalker", "clock_position": null, "supply": 134, "frame": 14958, "time": "15:34"}, {"is_worker": false, "name": "Stalker", "clock_position": null, "supply": 134, "frame": 14961, "time": "15:35"}, {"is_worker": false, "name": "Stalker", "clock_position": null, "supply": 134, "frame": 14989, "time": "15:36"}], "name": "Billowy", "clock_position": null, "level": 10, "region": "kr", "color": "1CA7EA", "race": "Protoss", "team": 2}, "2": {"abilities": [], "uid": 2344207, "is_human": true, "supply": [[0, 6], [1, 6], [160, 6], [320, 8], [480, 8], [640, 9], [800, 9], [960, 10], [1120, 10], [1280, 12], [1440, 13], [1600, 13], [1760, 14], [1920, 15], [2080, 15], [2240, 14], [2400, 16], [2560, 16], [2720, 16], [2880, 16], [3040, 16], [3200, 17], [3360, 17], [3520, 18], [3680, 18], [3840, 20], [4000, 20], [4160, 19], [4320, 22], [4480, 24], [4640, 26], [4800, 26], [4960, 28], [5120, 28], [5280, 32], [5440, 34], [5600, 35], [5760, 40], [5920, 42], [6080, 43], [6240, 46], [6400, 51], [6560, 51], [6720, 54], [6880, 55], [7040, 62], [7200, 61], [7360, 62], [7520, 62], [7680, 65], [7840, 67], [8000, 64], [8160, 65], [8320, 66], [8480, 72], [8640, 76], [8800, 74], [8960, 75], [9120, 76], [9280, 73], [9440, 81], [9600, 80], [9760, 80], [9920, 87], [10080, 87], [10240, 87], [10400, 102], [10560, 102], [10720, 101], [10880, 100], [11040, 100], [11200, 108], [11360, 114], [11520, 126], [11680, 126], [11840, 136], [12000, 136], [12160, 136], [12320, 136], [12480, 138], [12640, 161], [12800, 161], [12960, 160], [13120, 172], [13280, 188], [13440, 187], [13600, 186], [13760, 181], [13920, 189], [14080, 189], [14240, 179], [14400, 156], [14560, 140], [14720, 128], [14880, 125], [15040, 103], [15061, 101], [15061, 101]], "handicap": 100, "is_winner": false, "pick_race": "Zerg", "unitsLost": [{"frame": 3693, "killer": null, "name": "Drone", "clock_position": null, "time": "3:50"}, {"frame": 3961, "killer": null, "name": "Drone", "clock_position": null, "time": "4:07"}, {"frame": 5635, "killer": null, "name": "Drone", "clock_position": null, "time": "5:52"}, {"frame": 6408, "killer": null, "name": "Drone", "clock_position": null, "time": "6:40"}, {"frame": 6410, "killer": null, "name": "Drone", "clock_position": null, "time": "6:40"}, {"frame": 7289, "killer": 1, "name": "Overlord", "clock_position": null, "time": "7:35"}, {"frame": 7689, "killer": 1, "name": "Zergling", "clock_position": null, "time": "8:00"}, {"frame": 7917, "killer": null, "name": "Drone", "clock_position": null, "time": "8:14"}, {"frame": 7922, "killer": null, "name": "Drone", "clock_position": null, "time": "8:15"}, {"frame": 8008, "killer": null, "name": "Drone", "clock_position": null, "time": "8:20"}, {"frame": 8128, "killer": null, "name": "Drone", "clock_position": null, "time": "8:28"}, {"frame": 8151, "killer": null, "name": "Drone", "clock_position": null, "time": "8:29"}, {"frame": 8218, "killer": 1, "name": "Overlord", "clock_position": null, "time": "8:33"}, {"frame": 8319, "killer": null, "name": "Drone", "clock_position": null, "time": "8:39"}, {"frame": 8335, "killer": null, "name": "Drone", "clock_position": null, "time": "8:40"}, {"frame": 8389, "killer": null, "name": "Drone", "clock_position": null, "time": "8:44"}, {"frame": 8420, "killer": null, "name": "Drone", "clock_position": null, "time": "8:46"}, {"frame": 8658, "killer": 1, "name": "Drone", "clock_position": null, "time": "9:01"}, {"frame": 8684, "killer": null, "name": "Drone", "clock_position": null, "time": "9:02"}, {"frame": 8697, "killer": 1, "name": "Drone", "clock_position": null, "time": "9:03"}, {"frame": 9117, "killer": null, "name": "Drone", "clock_position": null, "time": "9:29"}, {"frame": 9153, "killer": null, "name": "Drone", "clock_position": null, "time": "9:32"}, {"frame": 9257, "killer": 1, "name": "Drone", "clock_position": null, "time": "9:38"}, {"frame": 9272, "killer": 1, "name": "Drone", "clock_position": null, "time": "9:39"}, {"frame": 9292, "killer": 1, "name": "Drone", "clock_position": null, "time": "9:40"}, {"frame": 9314, "killer": 1, "name": "Drone", "clock_position": null, "time": "9:42"}, {"frame": 9323, "killer": null, "name": "Drone", "clock_position": null, "time": "9:42"}, {"frame": 9574, "killer": 1, "name": "Drone", "clock_position": null, "time": "9:58"}, {"frame": 9594, "killer": 1, "name": "Drone", "clock_position": null, "time": "9:59"}, {"frame": 10045, "killer": null, "name": "Drone", "clock_position": null, "time": "10:27"}, {"frame": 11183, "killer": null, "name": "Drone", "clock_position": null, "time": "11:38"}, {"frame": 11353, "killer": 1, "name": "Zergling", "clock_position": null, "time": "11:49"}, {"frame": 11863, "killer": null, "name": "Drone", "clock_position": null, "time": "12:21"}, {"frame": 12375, "killer": null, "name": "Drone", "clock_position": null, "time": "12:53"}, {"frame": 12451, "killer": 2, "name": "ChangelingZealot", "clock_position": null, "time": "12:58"}, {"frame": 13421, "killer": 1, "name": "Zergling", "clock_position": null, "time": "13:58"}, {"frame": 13486, "killer": 1, "name": "Zergling", "clock_position": null, "time": "14:02"}, {"frame": 13495, "killer": 1, "name": "Zergling", "clock_position": null, "time": "14:03"}, {"frame": 13632, "killer": 1, "name": "Queen", "clock_position": null, "time": "14:12"}, {"frame": 13654, "killer": 1, "name": "Drone", "clock_position": null, "time": "14:13"}, {"frame": 13660, "killer": 1, "name": "Drone", "clock_position": null, "time": "14:13"}, {"frame": 13675, "killer": null, "name": "Drone", "clock_position": null, "time": "14:14"}, {"frame": 13682, "killer": 1, "name": "Drone", "clock_position": null, "time": "14:15"}, {"frame": 13749, "killer": 1, "name": "Hatchery", "clock_position": null, "time": "14:19"}, {"frame": 14160, "killer": 2, "name": "ChangelingZealot", "clock_position": null, "time": "14:45"}, {"frame": 14189, "killer": 1, "name": "Zergling", "clock_position": null, "time": "14:46"}, {"frame": 14190, "killer": 1, "name": "Zergling", "clock_position": null, "time": "14:46"}, {"frame": 14192, "killer": 1, "name": "Zergling", "clock_position": null, "time": "14:47"}, {"frame": 14193, "killer": 1, "name": "Zergling", "clock_position": null, "time": "14:47"}, {"frame": 14195, "killer": 1, "name": "Zergling", "clock_position": null, "time": "14:47"}, {"frame": 14195, "killer": 1, "name": "Zergling", "clock_position": null, "time": "14:47"}, {"frame": 14202, "killer": 1, "name": "Zergling", "clock_position": null, "time": "14:47"}, {"frame": 14211, "killer": 1, "name": "Zergling", "clock_position": null, "time": "14:48"}, {"frame": 14213, "killer": 1, "name": "Zergling", "clock_position": null, "time": "14:48"}, {"frame": 14218, "killer": 1, "name": "Zergling", "clock_position": null, "time": "14:48"}, {"frame": 14219, "killer": 1, "name": "Zergling", "clock_position": null, "time": "14:48"}, {"frame": 14220, "killer": 1, "name": "Zergling", "clock_position": null, "time": "14:48"}, {"frame": 14221, "killer": 1, "name": "Zergling", "clock_position": null, "time": "14:48"}, {"frame": 14221, "killer": 1, "name": "Zergling", "clock_position": null, "time": "14:48"}, {"frame": 14222, "killer": 1, "name": "Zergling", "clock_position": null, "time": "14:48"}, {"frame": 14222, "killer": 1, "name": "Zergling", "clock_position": null, "time": "14:48"}, {"frame": 14222, "killer": 1, "name": "Zergling", "clock_position": null, "time": "14:48"}, {"frame": 14222, "killer": 1, "name": "Zergling", "clock_position": null, "time": "14:48"}, {"frame": 14233, "killer": 1, "name": "Zergling", "clock_position": null, "time": "14:49"}, {"frame": 14237, "killer": 1, "name": "Zergling", "clock_position": null, "time": "14:49"}, {"frame": 14248, "killer": 1, "name": "Zergling", "clock_position": null, "time": "14:50"}, {"frame": 14258, "killer": 1, "name": "Zergling", "clock_position": null, "time": "14:51"}, {"frame": 14268, "killer": 1, "name": "Hydralisk", "clock_position": null, "time": "14:51"}, {"frame": 14272, "killer": 1, "name": "Roach", "clock_position": null, "time": "14:52"}, {"frame": 14274, "killer": 1, "name": "Roach", "clock_position": null, "time": "14:52"}, {"frame": 14276, "killer": 1, "name": "Roach", "clock_position": null, "time": "14:52"}, {"frame": 14289, "killer": 1, "name": "Roach", "clock_position": null, "time": "14:53"}, {"frame": 14291, "killer": 1, "name": "Hydralisk", "clock_position": null, "time": "14:53"}, {"frame": 14292, "killer": 1, "name": "Roach", "clock_position": null, "time": "14:53"}, {"frame": 14300, "killer": 1, "name": "Roach", "clock_position": null, "time": "14:53"}, {"frame": 14318, "killer": 1, "name": "Roach", "clock_position": null, "time": "14:54"}, {"frame": 14323, "killer": 1, "name": "Hydralisk", "clock_position": null, "time": "14:55"}, {"frame": 14330, "killer": 1, "name": "Roach", "clock_position": null, "time": "14:55"}, {"frame": 14340, "killer": 1, "name": "Hydralisk", "clock_position": null, "time": "14:56"}, {"frame": 14343, "killer": 1, "name": "Corruptor", "clock_position": null, "time": "14:56"}, {"frame": 14353, "killer": 1, "name": "Roach", "clock_position": null, "time": "14:57"}, {"frame": 14358, "killer": 1, "name": "Roach", "clock_position": null, "time": "14:57"}, {"frame": 14361, "killer": 1, "name": "Roach", "clock_position": null, "time": "14:57"}, {"frame": 14363, "killer": 1, "name": "Hydralisk", "clock_position": null, "time": "14:57"}, {"frame": 14378, "killer": 1, "name": "Roach", "clock_position": null, "time": "14:58"}, {"frame": 14386, "killer": 1, "name": "Hydralisk", "clock_position": null, "time": "14:59"}, {"frame": 14390, "killer": 1, "name": "Hydralisk", "clock_position": null, "time": "14:59"}, {"frame": 14412, "killer": 1, "name": "Hydralisk", "clock_position": null, "time": "15:00"}, {"frame": 14413, "killer": 1, "name": "Roach", "clock_position": null, "time": "15:00"}, {"frame": 14426, "killer": 1, "name": "Roach", "clock_position": null, "time": "15:01"}, {"frame": 14430, "killer": 1, "name": "Hydralisk", "clock_position": null, "time": "15:01"}, {"frame": 14435, "killer": 1, "name": "Roach", "clock_position": null, "time": "15:02"}, {"frame": 14451, "killer": 1, "name": "Roach", "clock_position": null, "time": "15:03"}, {"frame": 14468, "killer": 1, "name": "Roach", "clock_position": null, "time": "15:04"}, {"frame": 14472, "killer": 1, "name": "Roach", "clock_position": null, "time": "15:04"}, {"frame": 14475, "killer": 1, "name": "Roach", "clock_position": null, "time": "15:04"}, {"frame": 14479, "killer": 1, "name": "Roach", "clock_position": null, "time": "15:04"}, {"frame": 14494, "killer": 1, "name": "Hydralisk", "clock_position": null, "time": "15:05"}, {"frame": 14494, "killer": 1, "name": "Roach", "clock_position": null, "time": "15:05"}, {"frame": 14508, "killer": 1, "name": "Roach", "clock_position": null, "time": "15:06"}, {"frame": 14512, "killer": 1, "name": "Hydralisk", "clock_position": null, "time": "15:07"}, {"frame": 14518, "killer": 1, "name": "Hydralisk", "clock_position": null, "time": "15:07"}, {"frame": 14525, "killer": 1, "name": "Corruptor", "clock_position": null, "time": "15:07"}, {"frame": 14570, "killer": 1, "name": "Corruptor", "clock_position": null, "time": "15:10"}, {"frame": 14573, "killer": 1, "name": "Corruptor", "clock_position": null, "time": "15:10"}, {"frame": 14590, "killer": 1, "name": "Corruptor", "clock_position": null, "time": "15:11"}, {"frame": 14593, "killer": 1, "name": "Corruptor", "clock_position": null, "time": "15:12"}, {"frame": 14603, "killer": 1, "name": "Corruptor", "clock_position": null, "time": "15:12"}, {"frame": 14617, "killer": 1, "name": "Corruptor", "clock_position": null, "time": "15:13"}, {"frame": 14628, "killer": 1, "name": "Corruptor", "clock_position": null, "time": "15:14"}, {"frame": 14653, "killer": 1, "name": "Corruptor", "clock_position": null, "time": "15:15"}, {"frame": 14719, "killer": 1, "name": "Overlord", "clock_position": null, "time": "15:19"}, {"frame": 14789, "killer": 1, "name": "NydusNetwork", "clock_position": null, "time": "15:24"}, {"frame": 14799, "killer": 1, "name": "Queen", "clock_position": null, "time": "15:24"}, {"frame": 14850, "killer": 1, "name": "Drone", "clock_position": null, "time": "15:28"}, {"frame": 14875, "killer": 1, "name": "Drone", "clock_position": null, "time": "15:29"}, {"frame": 14876, "killer": 1, "name": "Roach", "clock_position": null, "time": "15:29"}, {"frame": 14876, "killer": 1, "name": "Drone", "clock_position": null, "time": "15:29"}, {"frame": 14899, "killer": 1, "name": "Drone", "clock_position": null, "time": "15:31"}, {"frame": 14899, "killer": 1, "name": "Drone", "clock_position": null, "time": "15:31"}, {"frame": 14904, "killer": 1, "name": "Drone", "clock_position": null, "time": "15:31"}, {"frame": 14910, "killer": 1, "name": "Drone", "clock_position": null, "time": "15:31"}, {"frame": 14922, "killer": 1, "name": "Drone", "clock_position": null, "time": "15:32"}, {"frame": 14923, "killer": 1, "name": "Drone", "clock_position": null, "time": "15:32"}, {"frame": 14924, "killer": 1, "name": "Drone", "clock_position": null, "time": "15:32"}, {"frame": 14933, "killer": 1, "name": "Drone", "clock_position": null, "time": "15:33"}, {"frame": 14934, "killer": 1, "name": "Drone", "clock_position": null, "time": "15:33"}, {"frame": 14945, "killer": 1, "name": "Drone", "clock_position": null, "time": "15:34"}, {"frame": 14945, "killer": 1, "name": "Drone", "clock_position": null, "time": "15:34"}, {"frame": 14950, "killer": 1, "name": "Drone", "clock_position": null, "time": "15:34"}, {"frame": 14963, "killer": 1, "name": "Drone", "clock_position": null, "time": "15:35"}, {"frame": 14969, "killer": 1, "name": "Drone", "clock_position": null, "time": "15:35"}, {"frame": 14989, "killer": 1, "name": "Roach", "clock_position": null, "time": "15:36"}, {"frame": 14999, "killer": 1, "name": "Roach", "clock_position": null, "time": "15:37"}, {"frame": 15012, "killer": 1, "name": "Roach", "clock_position": null, "time": "15:38"}, {"frame": 15017, "killer": 1, "name": "Drone", "clock_position": null, "time": "15:38"}, {"frame": 15020, "killer": 1, "name": "Roach", "clock_position": null, "time": "15:38"}, {"frame": 15023, "killer": 1, "name": "Roach", "clock_position": null, "time": "15:38"}, {"frame": 15034, "killer": 1, "name": "Drone", "clock_position": null, "time": "15:39"}, {"frame": 15050, "killer": 1, "name": "Roach", "clock_position": null, "time": "15:40"}, {"frame": 15063, "killer": 1, "name": "Roach", "clock_position": null, "time": "15:41"}, {"frame": 15070, "killer": 1, "name": "Roach", "clock_position": null, "time": "15:41"}, {"frame": 15073, "killer": 1, "name": "Roach", "clock_position": null, "time": "15:42"}, {"frame": 15081, "killer": 1, "name": "Roach", "clock_position": null, "time": "15:42"}, {"frame": 15088, "killer": 1, "name": "Roach", "clock_position": null, "time": "15:43"}, {"frame": 15115, "killer": 1, "name": "Roach", "clock_position": null, "time": "15:44"}, {"frame": 15122, "killer": 1, "name": "Roach", "clock_position": null, "time": "15:45"}, {"frame": 15130, "killer": 1, "name": "Overlord", "clock_position": null, "time": "15:45"}, {"frame": 15132, "killer": 1, "name": "Roach", "clock_position": null, "time": "15:45"}], "result": "Loss", "league": 8, "buildOrder": [{"is_worker": true, "name": "Drone", "clock_position": null, "supply": 6, "frame": 165, "time": "0:10"}, {"is_worker": true, "name": "Drone", "clock_position": null, "supply": 6, "frame": 255, "time": "0:15"}, {"is_worker": true, "name": "Drone", "clock_position": null, "supply": 4, "frame": 480, "time": "0:30"}, {"is_worker": false, "name": "Overlord", "clock_position": null, "supply": 9, "frame": 767, "time": "0:47"}, {"is_worker": true, "name": "Drone", "clock_position": null, "supply": 9, "frame": 881, "time": "0:55"}, {"is_worker": true, "name": "Drone", "clock_position": null, "supply": 10, "frame": 1181, "time": "1:13"}, {"is_worker": true, "name": "Drone", "clock_position": null, "supply": 10, "frame": 1184, "time": "1:14"}, {"is_worker": true, "name": "Drone", "clock_position": null, "supply": 12, "frame": 1384, "time": "1:26"}, {"is_worker": true, "name": "Drone", "clock_position": null, "supply": 13, "frame": 1636, "time": "1:42"}, {"is_worker": true, "name": "Drone", "clock_position": null, "supply": 14, "frame": 1861, "time": "1:56"}, {"is_worker": false, "name": "Hatchery", "clock_position": null, "supply": 15, "frame": 2092, "time": "2:10"}, {"is_worker": true, "name": "Drone", "clock_position": null, "supply": 14, "frame": 2270, "time": "2:21"}, {"is_worker": true, "name": "Drone", "clock_position": null, "supply": 14, "frame": 2355, "time": "2:27"}, {"is_worker": false, "name": "SpawningPool", "clock_position": null, "supply": 16, "frame": 2921, "time": "3:02"}, {"is_worker": true, "name": "Drone", "clock_position": null, "supply": 16, "frame": 2926, "time": "3:02"}, {"is_worker": true, "name": "Drone", "clock_position": null, "supply": 16, "frame": 3044, "time": "3:10"}, {"is_worker": true, "name": "Drone", "clock_position": null, "supply": 17, "frame": 3387, "time": "3:31"}, {"is_worker": false, "name": "Overlord", "clock_position": null, "supply": 17, "frame": 3407, "time": "3:32"}, {"is_worker": true, "name": "Drone", "clock_position": null, "supply": 18, "frame": 3783, "time": "3:56"}, {"is_worker": true, "name": "Drone", "clock_position": null, "supply": 18, "frame": 3786, "time": "3:56"}, {"is_worker": false, "name": "Hatchery", "clock_position": null, "supply": 20, "frame": 4034, "time": "4:12"}, {"is_worker": false, "name": "Queen", "clock_position": null, "supply": 19, "frame": 4214, "time": "4:23"}, {"is_worker": false, "name": "Zergling", "clock_position": null, "supply": 19, "frame": 4286, "time": "4:27"}, {"is_worker": false, "name": "Zergling", "clock_position": null, "supply": 19, "frame": 4286, "time": "4:27"}, {"is_worker": true, "name": "Drone", "clock_position": null, "supply": 22, "frame": 4359, "time": "4:32"}, {"is_worker": true, "name": "Drone", "clock_position": null, "supply": 22, "frame": 4425, "time": "4:36"}, {"is_worker": false, "name": "Queen", "clock_position": null, "supply": 24, "frame": 4595, "time": "4:47"}, {"is_worker": false, "name": "Overlord", "clock_position": null, "supply": 26, "frame": 4726, "time": "4:55"}, {"is_worker": true, "name": "Drone", "clock_position": null, "supply": 26, "frame": 4810, "time": "5:00"}, {"is_worker": true, "name": "Drone", "clock_position": null, "supply": 26, "frame": 4838, "time": "5:02"}, {"is_worker": true, "name": "Drone", "clock_position": null, "supply": 28, "frame": 5128, "time": "5:20"}, {"is_worker": true, "name": "Drone", "clock_position": null, "supply": 28, "frame": 5129, "time": "5:20"}, {"is_worker": true, "name": "Drone", "clock_position": null, "supply": 28, "frame": 5130, "time": "5:20"}, {"is_worker": true, "name": "Drone", "clock_position": null, "supply": 28, "frame": 5130, "time": "5:20"}, {"is_worker": false, "name": "Overlord", "clock_position": null, "supply": 28, "frame": 5265, "time": "5:29"}, {"is_worker": false, "name": "Queen", "clock_position": null, "supply": 32, "frame": 5350, "time": "5:34"}, {"is_worker": true, "name": "Drone", "clock_position": null, "supply": 34, "frame": 5585, "time": "5:49"}, {"is_worker": true, "name": "Drone", "clock_position": null, "supply": 35, "frame": 5603, "time": "5:50"}, {"is_worker": true, "name": "Drone", "clock_position": null, "supply": 35, "frame": 5639, "time": "5:52"}, {"is_worker": true, "name": "Drone", "clock_position": null, "supply": 35, "frame": 5671, "time": "5:54"}, {"is_worker": true, "name": "Drone", "clock_position": null, "supply": 35, "frame": 5674, "time": "5:54"}, {"is_worker": true, "name": "Drone", "clock_position": null, "supply": 35, "frame": 5759, "time": "5:59"}, {"is_worker": true, "name": "Drone", "clock_position": null, "supply": 40, "frame": 5766, "time": "6:00"}, {"is_worker": true, "name": "Drone", "clock_position": null, "supply": 40, "frame": 5766, "time": "6:00"}, {"is_worker": false, "name": "Overlord", "clock_position": null, "supply": 40, "frame": 5848, "time": "6:05"}, {"is_worker": false, "name": "Extractor", "clock_position": null, "supply": 42, "frame": 5927, "time": "6:10"}, {"is_worker": false, "name": "Extractor", "clock_position": null, "supply": 42, "frame": 5930, "time": "6:10"}, {"is_worker": true, "name": "Drone", "clock_position": null, "supply": 42, "frame": 5934, "time": "6:10"}, {"is_worker": true, "name": "Drone", "clock_position": null, "supply": 42, "frame": 5936, "time": "6:11"}, {"is_worker": true, "name": "Drone", "clock_position": null, "supply": 42, "frame": 6004, "time": "6:15"}, {"is_worker": true, "name": "Drone", "clock_position": null, "supply": 43, "frame": 6106, "time": "6:21"}, {"is_worker": true, "name": "Drone", "clock_position": null, "supply": 43, "frame": 6144, "time": "6:24"}, {"is_worker": true, "name": "Drone", "clock_position": null, "supply": 43, "frame": 6148, "time": "6:24"}, {"is_worker": false, "name": "Overlord", "clock_position": null, "supply": 43, "frame": 6231, "time": "6:29"}, {"is_worker": true, "name": "Drone", "clock_position": null, "supply": 46, "frame": 6277, "time": "6:32"}, {"is_worker": true, "name": "Drone", "clock_position": null, "supply": 46, "frame": 6282, "time": "6:32"}, {"is_worker": true, "name": "Drone", "clock_position": null, "supply": 46, "frame": 6383, "time": "6:38"}, {"is_worker": true, "name": "Drone", "clock_position": null, "supply": 46, "frame": 6389, "time": "6:39"}, {"is_worker": true, "name": "Drone", "clock_position": null, "supply": 46, "frame": 6389, "time": "6:39"}, {"is_worker": true, "name": "Drone", "clock_position": null, "supply": 51, "frame": 6623, "time": "6:53"}, {"is_worker": true, "name": "Drone", "clock_position": null, "supply": 51, "frame": 6628, "time": "6:54"}, {"is_worker": true, "name": "Drone", "clock_position": null, "supply": 51, "frame": 6628, "time": "6:54"}, {"is_worker": false, "name": "Overlord", "clock_position": null, "supply": 51, "frame": 6716, "time": "6:59"}, {"is_worker": false, "name": "Zergling", "clock_position": null, "supply": 54, "frame": 6854, "time": "7:08"}, {"is_worker": false, "name": "Zergling", "clock_position": null, "supply": 54, "frame": 6854, "time": "7:08"}, {"is_worker": true, "name": "Drone", "clock_position": null, "supply": 55, "frame": 6924, "time": "7:12"}, {"is_worker": true, "name": "Drone", "clock_position": null, "supply": 55, "frame": 6930, "time": "7:13"}, {"is_worker": true, "name": "Drone", "clock_position": null, "supply": 55, "frame": 6930, "time": "7:13"}, {"is_worker": true, "name": "Drone", "clock_position": null, "supply": 55, "frame": 6931, "time": "7:13"}, {"is_worker": true, "name": "Drone", "clock_position": null, "supply": 55, "frame": 6931, "time": "7:13"}, {"is_worker": true, "name": "Drone", "clock_position": null, "supply": 55, "frame": 6932, "time": "7:13"}, {"is_worker": true, "name": "Drone", "clock_position": null, "supply": 55, "frame": 6932, "time": "7:13"}, {"is_worker": false, "name": "Lair", "clock_position": null, "supply": 62, "frame": 7053, "time": "7:20"}, {"is_worker": false, "name": "RoachWarren", "clock_position": null, "supply": 62, "frame": 7128, "time": "7:25"}, {"is_worker": false, "name": "Overlord", "clock_position": null, "supply": 62, "frame": 7146, "time": "7:26"}, {"is_worker": false, "name": "Overlord", "clock_position": null, "supply": 62, "frame": 7159, "time": "7:27"}, {"is_worker": true, "name": "Drone", "clock_position": null, "supply": 61, "frame": 7301, "time": "7:36"}, {"is_worker": false, "name": "zerglingmovementspeed", "clock_position": null, "supply": 62, "frame": 7420, "time": "7:43"}, {"is_worker": false, "name": "Extractor", "clock_position": null, "supply": 62, "frame": 7437, "time": "7:44"}, {"is_worker": true, "name": "Drone", "clock_position": null, "supply": 62, "frame": 7439, "time": "7:44"}, {"is_worker": false, "name": "Extractor", "clock_position": null, "supply": 62, "frame": 7441, "time": "7:45"}, {"is_worker": true, "name": "Drone", "clock_position": null, "supply": 62, "frame": 7441, "time": "7:45"}, {"is_worker": false, "name": "Overlord", "clock_position": null, "supply": 62, "frame": 7476, "time": "7:47"}, {"is_worker": true, "name": "Drone", "clock_position": null, "supply": 62, "frame": 7548, "time": "7:51"}, {"is_worker": true, "name": "Drone", "clock_position": null, "supply": 62, "frame": 7549, "time": "7:51"}, {"is_worker": true, "name": "Drone", "clock_position": null, "supply": 62, "frame": 7549, "time": "7:51"}, {"is_worker": true, "name": "Drone", "clock_position": null, "supply": 62, "frame": 7550, "time": "7:51"}, {"is_worker": true, "name": "Drone", "clock_position": null, "supply": 62, "frame": 7550, "time": "7:51"}, {"is_worker": false, "name": "SporeCrawler", "clock_position": null, "supply": 62, "frame": 7647, "time": "7:57"}, {"is_worker": false, "name": "SporeCrawler", "clock_position": null, "supply": 62, "frame": 7671, "time": "7:59"}, {"is_worker": false, "name": "Zergling", "clock_position": null, "supply": 65, "frame": 7756, "time": "8:04"}, {"is_worker": false, "name": "Zergling", "clock_position": null, "supply": 65, "frame": 7756, "time": "8:04"}, {"is_worker": true, "name": "Drone", "clock_position": null, "supply": 65, "frame": 7784, "time": "8:06"}, {"is_worker": true, "name": "Drone", "clock_position": null, "supply": 65, "frame": 7790, "time": "8:06"}, {"is_worker": true, "name": "Drone", "clock_position": null, "supply": 65, "frame": 7791, "time": "8:06"}, {"is_worker": false, "name": "SporeCrawler", "clock_position": null, "supply": 65, "frame": 7839, "time": "8:09"}, {"is_worker": false, "name": "SporeCrawler", "clock_position": null, "supply": 67, "frame": 7855, "time": "8:10"}, {"is_worker": false, "name": "SporeCrawler", "clock_position": null, "supply": 67, "frame": 7909, "time": "8:14"}, {"is_worker": false, "name": "SporeCrawler", "clock_position": null, "supply": 67, "frame": 7939, "time": "8:16"}, {"is_worker": true, "name": "Drone", "clock_position": null, "supply": 64, "frame": 8004, "time": "8:20"}, {"is_worker": true, "name": "Drone", "clock_position": null, "supply": 64, "frame": 8009, "time": "8:20"}, {"is_worker": false, "name": "EvolutionChamber", "clock_position": null, "supply": 64, "frame": 8124, "time": "8:27"}, {"is_worker": false, "name": "Zergling", "clock_position": null, "supply": 65, "frame": 8241, "time": "8:35"}, {"is_worker": false, "name": "Zergling", "clock_position": null, "supply": 65, "frame": 8241, "time": "8:35"}, {"is_worker": false, "name": "Overlord", "clock_position": null, "supply": 65, "frame": 8273, "time": "8:37"}, {"is_worker": false, "name": "Overlord", "clock_position": null, "supply": 65, "frame": 8276, "time": "8:37"}, {"is_worker": false, "name": "Overlord", "clock_position": null, "supply": 65, "frame": 8278, "time": "8:37"}, {"is_worker": false, "name": "Overlord", "clock_position": null, "supply": 65, "frame": 8282, "time": "8:37"}, {"is_worker": false, "name": "Overseer", "clock_position": null, "supply": 66, "frame": 8380, "time": "8:43"}, {"is_worker": false, "name": "Roach", "clock_position": null, "supply": 66, "frame": 8428, "time": "8:46"}, {"is_worker": false, "name": "Roach", "clock_position": null, "supply": 66, "frame": 8433, "time": "8:47"}, {"is_worker": false, "name": "Roach", "clock_position": null, "supply": 66, "frame": 8435, "time": "8:47"}, {"is_worker": true, "name": "Drone", "clock_position": null, "supply": 72, "frame": 8620, "time": "8:58"}, {"is_worker": true, "name": "Drone", "clock_position": null, "supply": 72, "frame": 8626, "time": "8:59"}, {"is_worker": true, "name": "Drone", "clock_position": null, "supply": 72, "frame": 8627, "time": "8:59"}, {"is_worker": true, "name": "Drone", "clock_position": null, "supply": 72, "frame": 8627, "time": "8:59"}, {"is_worker": true, "name": "Drone", "clock_position": null, "supply": 72, "frame": 8628, "time": "8:59"}, {"is_worker": false, "name": "Extractor", "clock_position": null, "supply": 72, "frame": 8636, "time": "8:59"}, {"is_worker": false, "name": "Extractor", "clock_position": null, "supply": 76, "frame": 8672, "time": "9:02"}, {"is_worker": false, "name": "HydraliskDen", "clock_position": null, "supply": 76, "frame": 8682, "time": "9:02"}, {"is_worker": false, "name": "Roach", "clock_position": null, "supply": 76, "frame": 8686, "time": "9:02"}, {"is_worker": true, "name": "Drone", "clock_position": null, "supply": 74, "frame": 8959, "time": "9:19"}, {"is_worker": true, "name": "Drone", "clock_position": null, "supply": 75, "frame": 8966, "time": "9:20"}, {"is_worker": false, "name": "Overlord", "clock_position": null, "supply": 75, "frame": 8978, "time": "9:21"}, {"is_worker": false, "name": "Overlord", "clock_position": null, "supply": 75, "frame": 8982, "time": "9:21"}, {"is_worker": false, "name": "Overlord", "clock_position": null, "supply": 75, "frame": 8985, "time": "9:21"}, {"is_worker": false, "name": "InfestationPit", "clock_position": null, "supply": 76, "frame": 9245, "time": "9:37"}, {"is_worker": true, "name": "Drone", "clock_position": null, "supply": 73, "frame": 9317, "time": "9:42"}, {"is_worker": true, "name": "Drone", "clock_position": null, "supply": 73, "frame": 9323, "time": "9:42"}, {"is_worker": true, "name": "Drone", "clock_position": null, "supply": 73, "frame": 9324, "time": "9:42"}, {"is_worker": true, "name": "Drone", "clock_position": null, "supply": 73, "frame": 9324, "time": "9:42"}, {"is_worker": true, "name": "Drone", "clock_position": null, "supply": 73, "frame": 9326, "time": "9:42"}, {"is_worker": true, "name": "Drone", "clock_position": null, "supply": 73, "frame": 9326, "time": "9:42"}, {"is_worker": true, "name": "Drone", "clock_position": null, "supply": 73, "frame": 9327, "time": "9:42"}, {"is_worker": true, "name": "Drone", "clock_position": null, "supply": 73, "frame": 9327, "time": "9:42"}, {"is_worker": true, "name": "Drone", "clock_position": null, "supply": 73, "frame": 9328, "time": "9:43"}, {"is_worker": true, "name": "Drone", "clock_position": null, "supply": 73, "frame": 9330, "time": "9:43"}, {"is_worker": true, "name": "Drone", "clock_position": null, "supply": 81, "frame": 9521, "time": "9:55"}, {"is_worker": true, "name": "Drone", "clock_position": null, "supply": 80, "frame": 9772, "time": "10:10"}, {"is_worker": false, "name": "Overlord", "clock_position": null, "supply": 80, "frame": 9776, "time": "10:11"}, {"is_worker": true, "name": "Drone", "clock_position": null, "supply": 80, "frame": 9778, "time": "10:11"}, {"is_worker": true, "name": "Drone", "clock_position": null, "supply": 80, "frame": 9778, "time": "10:11"}, {"is_worker": true, "name": "Drone", "clock_position": null, "supply": 80, "frame": 9779, "time": "10:11"}, {"is_worker": true, "name": "Drone", "clock_position": null, "supply": 80, "frame": 9794, "time": "10:12"}, {"is_worker": true, "name": "Drone", "clock_position": null, "supply": 80, "frame": 9799, "time": "10:12"}, {"is_worker": true, "name": "Drone", "clock_position": null, "supply": 80, "frame": 9801, "time": "10:12"}, {"is_worker": false, "name": "Hatchery", "clock_position": null, "supply": 87, "frame": 10263, "time": "10:41"}, {"is_worker": false, "name": "Hydralisk", "clock_position": null, "supply": 87, "frame": 10347, "time": "10:46"}, {"is_worker": false, "name": "Hydralisk", "clock_position": null, "supply": 87, "frame": 10353, "time": "10:47"}, {"is_worker": false, "name": "Hydralisk", "clock_position": null, "supply": 87, "frame": 10354, "time": "10:47"}, {"is_worker": false, "name": "Hydralisk", "clock_position": null, "supply": 87, "frame": 10354, "time": "10:47"}, {"is_worker": false, "name": "Hydralisk", "clock_position": null, "supply": 87, "frame": 10355, "time": "10:47"}, {"is_worker": false, "name": "Hydralisk", "clock_position": null, "supply": 87, "frame": 10355, "time": "10:47"}, {"is_worker": false, "name": "Hydralisk", "clock_position": null, "supply": 87, "frame": 10357, "time": "10:47"}, {"is_worker": false, "name": "Hydralisk", "clock_position": null, "supply": 87, "frame": 10383, "time": "10:48"}, {"is_worker": false, "name": "GlialReconstitution", "clock_position": null, "supply": 102, "frame": 10509, "time": "10:56"}, {"is_worker": false, "name": "EvolutionChamber", "clock_position": null, "supply": 102, "frame": 10623, "time": "11:03"}, {"is_worker": false, "name": "Overlord", "clock_position": null, "supply": 102, "frame": 10641, "time": "11:05"}, {"is_worker": false, "name": "Overlord", "clock_position": null, "supply": 102, "frame": 10643, "time": "11:05"}, {"is_worker": false, "name": "Overlord", "clock_position": null, "supply": 102, "frame": 10646, "time": "11:05"}, {"is_worker": false, "name": "Overlord", "clock_position": null, "supply": 102, "frame": 10650, "time": "11:05"}, {"is_worker": false, "name": "hydraliskspeed", "clock_position": null, "supply": 102, "frame": 10716, "time": "11:09"}, {"is_worker": false, "name": "Spire", "clock_position": null, "supply": 101, "frame": 10775, "time": "11:13"}, {"is_worker": false, "name": "Overseer", "clock_position": null, "supply": 100, "frame": 10957, "time": "11:24"}, {"is_worker": false, "name": "ZergMissileWeaponsLevel1", "clock_position": null, "supply": 100, "frame": 11086, "time": "11:32"}, {"is_worker": false, "name": "Hydralisk", "clock_position": null, "supply": 100, "frame": 11136, "time": "11:36"}, {"is_worker": false, "name": "Hydralisk", "clock_position": null, "supply": 100, "frame": 11140, "time": "11:36"}, {"is_worker": false, "name": "Hydralisk", "clock_position": null, "supply": 100, "frame": 11143, "time": "11:36"}, {"is_worker": false, "name": "Hydralisk", "clock_position": null, "supply": 100, "frame": 11147, "time": "11:36"}, {"is_worker": false, "name": "Overlord", "clock_position": null, "supply": 100, "frame": 11194, "time": "11:39"}, {"is_worker": false, "name": "Overlord", "clock_position": null, "supply": 100, "frame": 11198, "time": "11:39"}, {"is_worker": false, "name": "Overlord", "clock_position": null, "supply": 71, "frame": 11200, "time": "11:40"}, {"is_worker": false, "name": "Overlord", "clock_position": null, "supply": 108, "frame": 11205, "time": "11:40"}, {"is_worker": false, "name": "Roach", "clock_position": null, "supply": 108, "frame": 11284, "time": "11:45"}, {"is_worker": false, "name": "Roach", "clock_position": null, "supply": 108, "frame": 11289, "time": "11:45"}, {"is_worker": false, "name": "Roach", "clock_position": null, "supply": 108, "frame": 11289, "time": "11:45"}, {"is_worker": false, "name": "Roach", "clock_position": null, "supply": 114, "frame": 11470, "time": "11:56"}, {"is_worker": false, "name": "Roach", "clock_position": null, "supply": 114, "frame": 11475, "time": "11:57"}, {"is_worker": false, "name": "Roach", "clock_position": null, "supply": 114, "frame": 11476, "time": "11:57"}, {"is_worker": false, "name": "Roach", "clock_position": null, "supply": 114, "frame": 11476, "time": "11:57"}, {"is_worker": false, "name": "Roach", "clock_position": null, "supply": 114, "frame": 11478, "time": "11:57"}, {"is_worker": false, "name": "Roach", "clock_position": null, "supply": 114, "frame": 11478, "time": "11:57"}, {"is_worker": false, "name": "Roach", "clock_position": null, "supply": 126, "frame": 11681, "time": "12:10"}, {"is_worker": false, "name": "Roach", "clock_position": null, "supply": 126, "frame": 11686, "time": "12:10"}, {"is_worker": false, "name": "Roach", "clock_position": null, "supply": 126, "frame": 11688, "time": "12:10"}, {"is_worker": false, "name": "Roach", "clock_position": null, "supply": 126, "frame": 11688, "time": "12:10"}, {"is_worker": false, "name": "Roach", "clock_position": null, "supply": 126, "frame": 11689, "time": "12:10"}, {"is_worker": false, "name": "Overseer", "clock_position": null, "supply": 136, "frame": 12328, "time": "12:50"}, {"is_worker": false, "name": "Queen", "clock_position": null, "supply": 136, "frame": 12445, "time": "12:57"}, {"is_worker": false, "name": "Corruptor", "clock_position": null, "supply": 138, "frame": 12502, "time": "13:01"}, {"is_worker": false, "name": "Corruptor", "clock_position": null, "supply": 138, "frame": 12507, "time": "13:01"}, {"is_worker": false, "name": "Corruptor", "clock_position": null, "supply": 138, "frame": 12509, "time": "13:01"}, {"is_worker": false, "name": "Corruptor", "clock_position": null, "supply": 138, "frame": 12509, "time": "13:01"}, {"is_worker": false, "name": "Corruptor", "clock_position": null, "supply": 138, "frame": 12510, "time": "13:01"}, {"is_worker": false, "name": "Corruptor", "clock_position": null, "supply": 138, "frame": 12510, "time": "13:01"}, {"is_worker": false, "name": "Corruptor", "clock_position": null, "supply": 138, "frame": 12511, "time": "13:01"}, {"is_worker": false, "name": "Corruptor", "clock_position": null, "supply": 138, "frame": 12511, "time": "13:01"}, {"is_worker": false, "name": "Corruptor", "clock_position": null, "supply": 138, "frame": 12534, "time": "13:03"}, {"is_worker": false, "name": "Corruptor", "clock_position": null, "supply": 138, "frame": 12537, "time": "13:03"}, {"is_worker": true, "name": "Drone", "clock_position": null, "supply": 138, "frame": 12589, "time": "13:06"}, {"is_worker": true, "name": "Drone", "clock_position": null, "supply": 138, "frame": 12595, "time": "13:07"}, {"is_worker": true, "name": "Drone", "clock_position": null, "supply": 138, "frame": 12596, "time": "13:07"}, {"is_worker": false, "name": "NydusNetwork", "clock_position": null, "supply": 161, "frame": 12874, "time": "13:24"}, {"is_worker": false, "name": "Zergling", "clock_position": null, "supply": 160, "frame": 13018, "time": "13:33"}, {"is_worker": false, "name": "Zergling", "clock_position": null, "supply": 160, "frame": 13018, "time": "13:33"}, {"is_worker": false, "name": "Zergling", "clock_position": null, "supply": 160, "frame": 13024, "time": "13:34"}, {"is_worker": false, "name": "Zergling", "clock_position": null, "supply": 160, "frame": 13024, "time": "13:34"}, {"is_worker": false, "name": "Zergling", "clock_position": null, "supply": 160, "frame": 13024, "time": "13:34"}, {"is_worker": false, "name": "Zergling", "clock_position": null, "supply": 160, "frame": 13024, "time": "13:34"}, {"is_worker": false, "name": "Zergling", "clock_position": null, "supply": 160, "frame": 13026, "time": "13:34"}, {"is_worker": false, "name": "Zergling", "clock_position": null, "supply": 160, "frame": 13026, "time": "13:34"}, {"is_worker": false, "name": "Zergling", "clock_position": null, "supply": 160, "frame": 13026, "time": "13:34"}, {"is_worker": false, "name": "Zergling", "clock_position": null, "supply": 160, "frame": 13026, "time": "13:34"}, {"is_worker": false, "name": "Zergling", "clock_position": null, "supply": 160, "frame": 13027, "time": "13:34"}, {"is_worker": false, "name": "Zergling", "clock_position": null, "supply": 160, "frame": 13027, "time": "13:34"}, {"is_worker": false, "name": "Zergling", "clock_position": null, "supply": 160, "frame": 13028, "time": "13:34"}, {"is_worker": false, "name": "Zergling", "clock_position": null, "supply": 160, "frame": 13028, "time": "13:34"}, {"is_worker": false, "name": "Zergling", "clock_position": null, "supply": 160, "frame": 13028, "time": "13:34"}, {"is_worker": false, "name": "Zergling", "clock_position": null, "supply": 160, "frame": 13028, "time": "13:34"}, {"is_worker": false, "name": "Zergling", "clock_position": null, "supply": 160, "frame": 13030, "time": "13:34"}, {"is_worker": false, "name": "Zergling", "clock_position": null, "supply": 160, "frame": 13030, "time": "13:34"}, {"is_worker": false, "name": "Zergling", "clock_position": null, "supply": 160, "frame": 13030, "time": "13:34"}, {"is_worker": false, "name": "Zergling", "clock_position": null, "supply": 160, "frame": 13030, "time": "13:34"}, {"is_worker": false, "name": "Zergling", "clock_position": null, "supply": 160, "frame": 13031, "time": "13:34"}, {"is_worker": false, "name": "Zergling", "clock_position": null, "supply": 160, "frame": 13031, "time": "13:34"}, {"is_worker": false, "name": "Zergling", "clock_position": null, "supply": 160, "frame": 13031, "time": "13:34"}, {"is_worker": false, "name": "Zergling", "clock_position": null, "supply": 160, "frame": 13031, "time": "13:34"}, {"is_worker": false, "name": "Roach", "clock_position": null, "supply": 172, "frame": 13241, "time": "13:47"}, {"is_worker": false, "name": "Roach", "clock_position": null, "supply": 172, "frame": 13246, "time": "13:47"}, {"is_worker": false, "name": "Roach", "clock_position": null, "supply": 172, "frame": 13248, "time": "13:48"}, {"is_worker": false, "name": "Roach", "clock_position": null, "supply": 172, "frame": 13248, "time": "13:48"}, {"is_worker": false, "name": "Roach", "clock_position": null, "supply": 172, "frame": 13249, "time": "13:48"}, {"is_worker": false, "name": "Roach", "clock_position": null, "supply": 172, "frame": 13249, "time": "13:48"}, {"is_worker": false, "name": "Roach", "clock_position": null, "supply": 172, "frame": 13250, "time": "13:48"}, {"is_worker": false, "name": "Roach", "clock_position": null, "supply": 172, "frame": 13250, "time": "13:48"}, {"is_worker": false, "name": "NydusCanal", "clock_position": null, "supply": 186, "frame": 13703, "time": "14:16"}, {"is_worker": false, "name": "Roach", "clock_position": null, "supply": 181, "frame": 13762, "time": "14:20"}, {"is_worker": false, "name": "Roach", "clock_position": null, "supply": 181, "frame": 13767, "time": "14:20"}, {"is_worker": false, "name": "Roach", "clock_position": null, "supply": 181, "frame": 13767, "time": "14:20"}, {"is_worker": false, "name": "Roach", "clock_position": null, "supply": 181, "frame": 13769, "time": "14:20"}, {"is_worker": false, "name": "Overlord", "clock_position": null, "supply": 181, "frame": 13914, "time": "14:29"}, {"is_worker": false, "name": "Overlord", "clock_position": null, "supply": 181, "frame": 13917, "time": "14:29"}, {"is_worker": false, "name": "Roach", "clock_position": null, "supply": 179, "frame": 14267, "time": "14:51"}, {"is_worker": false, "name": "Roach", "clock_position": null, "supply": 179, "frame": 14272, "time": "14:52"}, {"is_worker": false, "name": "Roach", "clock_position": null, "supply": 179, "frame": 14273, "time": "14:52"}, {"is_worker": false, "name": "Roach", "clock_position": null, "supply": 179, "frame": 14273, "time": "14:52"}, {"is_worker": false, "name": "Roach", "clock_position": null, "supply": 179, "frame": 14275, "time": "14:52"}, {"is_worker": false, "name": "Roach", "clock_position": null, "supply": 179, "frame": 14276, "time": "14:52"}, {"is_worker": false, "name": "Roach", "clock_position": null, "supply": 179, "frame": 14276, "time": "14:52"}, {"is_worker": false, "name": "Roach", "clock_position": null, "supply": 179, "frame": 14276, "time": "14:52"}, {"is_worker": false, "name": "Roach", "clock_position": null, "supply": 179, "frame": 14277, "time": "14:52"}, {"is_worker": false, "name": "Roach", "clock_position": null, "supply": 156, "frame": 14435, "time": "15:02"}, {"is_worker": false, "name": "Roach", "clock_position": null, "supply": 156, "frame": 14440, "time": "15:02"}, {"is_worker": false, "name": "Roach", "clock_position": null, "supply": 156, "frame": 14442, "time": "15:02"}, {"is_worker": false, "name": "Roach", "clock_position": null, "supply": 156, "frame": 14443, "time": "15:02"}, {"is_worker": false, "name": "Roach", "clock_position": null, "supply": 156, "frame": 14443, "time": "15:02"}, {"is_worker": false, "name": "Roach", "clock_position": null, "supply": 156, "frame": 14444, "time": "15:02"}, {"is_worker": false, "name": "Roach", "clock_position": null, "supply": 156, "frame": 14444, "time": "15:02"}, {"is_worker": false, "name": "Roach", "clock_position": null, "supply": 156, "frame": 14532, "time": "15:08"}, {"is_worker": false, "name": "Roach", "clock_position": null, "supply": 140, "frame": 14676, "time": "15:17"}, {"is_worker": false, "name": "Roach", "clock_position": null, "supply": 140, "frame": 14682, "time": "15:17"}], "name": "Symbol", "clock_position": null, "level": 15, "region": "kr", "color": "B4141E", "race": "Zerg", "team": 1}}, "buildOrderExtracted": true, "build": 29261, "unix_timestamp": 1397794491}